{
 "_id": "M02QMIJxDjMfDNKo",
 "name": "Повелитель зверей: Могучий спутник",
 "type": "feat",
 "img": "icons/creatures/abilities/lion-roar-yellow.webp",
 "system": {
  "description": {
   "value": "<p>Всякий раз, оканчивая Долгий отдых, вы можете даровать Зверю одно из следующих преимуществ. Выбранное преимущество длится до окончания следующего Долгого отдыха.</p><ul><li><strong>Гигантский спутник.</strong> Зверь становится на размер больше, совершает с Преимуществом проверки и спасброски Силы и увеличивает свой максимум хитов на значение, равное вашему удвоенному уровню Следопыта.</li><li><strong>Стремительный спутник.</strong> Скорость Зверя увеличивается на 15 футов. Если Зверь переместится не менее чем на 20 футов по прямой к существу и затем попадёт по нему рукопашной атакой в тот же ход, цель получает [[/damage 2d6]]{2d6 дополнительного урона} и не может использовать Реакции до начала своего следующего хода. Также Зверь совершает с Преимуществом проверки и спасброски Ловкости.</li><li><strong>Подземный спутник (требуется скорость копания).</strong> Зверь может копать сквозь сплошной камень со скоростью копания, уменьшенной вдвое, оставляя за собой туннель диаметром вдвое меньше своего размера.</li></ul><p><em>Переключаемый эффект «+15 фт скорости» (для Стремительного спутника) — перетащите на токен Зверя. Прочие преимущества примените вручную.</em></p>",
   "chat": ""
  },
  "source": {
   "custom": "Альтернативный Следопыт (Kasoda) v1.1",
   "rules": "2024",
   "revision": 1
  },
  "identifier": "beastmaster-mighty",
  "type": {
   "value": "class",
   "subtype": ""
  },
  "requirements": "Следопыт 11",
  "properties": [],
  "advancement": []
 },
 "effects": [
  {
   "_id": "W0kr7FUPe3MSqelR",
   "name": "Стремительный спутник: +15 фт скорости",
   "img": "icons/magic/movement/trail-streak-zigzag-yellow.webp",
   "type": "base",
   "changes": [
    {
     "key": "system.attributes.movement.walk",
     "mode": 2,
     "value": "15",
     "priority": 20
    }
   ],
   "disabled": true,
   "transfer": false,
   "duration": {
    "startTime": null,
    "seconds": null,
    "rounds": null,
    "turns": null
   },
   "description": "Перетащите на токен Зверя и включите на Долгий отдых: +15 фт к скорости.",
   "origin": null,
   "tint": "#ffffff",
   "statuses": [],
   "flags": {},
   "_key": "!items.effects!M02QMIJxDjMfDNKo.W0kr7FUPe3MSqelR"
  }
 ],
 "folder": null,
 "sort": 11000,
 "flags": {
  "sledopyt-kasoda-free": {
   "level": 11
  }
 },
 "_stats": {
  "systemId": "dnd5e"
 },
 "_key": "!items!M02QMIJxDjMfDNKo"
}